setup.py
onelogin_duo_sync/OneLogin.py
onelogin_duo_sync/__init__.py
onelogin_duo_sync/old_sync.py
onelogin_duo_sync.egg-info/PKG-INFO
onelogin_duo_sync.egg-info/SOURCES.txt
onelogin_duo_sync.egg-info/dependency_links.txt
onelogin_duo_sync.egg-info/not-zip-safe
onelogin_duo_sync.egg-info/requires.txt
onelogin_duo_sync.egg-info/top_level.txt