Metadata-Version: 1.0
Name: onelogin-duo-sync
Version: 0.1
Summary: simple script to mirror OneLogin users and groups to Duo
Home-page: https://github.com/ottiferous/OneLogin-Duo-Sync
Author: Andrew Marrone
Author-email: nope@nope.com
License: MIT
Platform: UNKNOWN
